LICENSE.txt
MANIFEST.in
README.rst
setup.py
linkuxit/__init__.py
linkuxit/contact/__init__.py
linkuxit/contact/admin.py
linkuxit/contact/cms_plugins.py
linkuxit/contact/forms.py
linkuxit/contact/models.py
linkuxit/contact/migrations/0001_initial.py
linkuxit/contact/migrations/0002_auto__add_field_message_sent_at.py
linkuxit/contact/migrations/__init__.py
linkuxit/contact/templates/aldryn_contact/contact.html
linkuxit/contact/templates/aldryn_contact/email.txt
linkuxit_aldryn_contact.egg-info/PKG-INFO
linkuxit_aldryn_contact.egg-info/SOURCES.txt
linkuxit_aldryn_contact.egg-info/dependency_links.txt
linkuxit_aldryn_contact.egg-info/not-zip-safe
linkuxit_aldryn_contact.egg-info/requires.txt
linkuxit_aldryn_contact.egg-info/top_level.txt